{
  "sampleId": 0,
  "timestamp": "2025-06-28T02:13:38.636Z",
  "rawKeystrokes": [
    {
      "key": "Tab",
      "type": "keyup",
      "timestamp": 11185.799999952316
    },
    {
      "key": "CapsLock",
      "type": "keydown",
      "timestamp": 11520.600000023842
    },
    {
      "key": "K",
      "type": "keydown",
      "timestamp": 11577.399999976158
    },
    {
      "key": "CapsLock",
      "type": "keyup",
      "timestamp": 11603
    },
    {
      "key": "CapsLock",
      "type": "keydown",
      "timestamp": 11655
    },
    {
      "key": "k",
      "type": "keyup",
      "timestamp": 11682
    },
    {
      "key": "i",
      "type": "keydown",
      "timestamp": 11757.600000023842
    },
    {
      "key": "CapsLock",
      "type": "keyup",
      "timestamp": 11795.699999928474
    },
    {
      "key": "i",
      "type": "keyup",
      "timestamp": 11848.600000023842
    },
    {
      "key": "n",
      "type": "keydown",
      "timestamp": 11910.899999976158
    },
    {
      "key": "g",
      "type": "keydown",
      "timestamp": 11967.100000023842
    },
    {
      "key": "n",
      "type": "keyup",
      "timestamp": 12035.299999952316
    },
    {
      "key": "g",
      "type": "keyup",
      "timestamp": 12095.5
    },
    {
      "key": "o",
      "type": "keydown",
      "timestamp": 12112.199999928474
    },
    {
      "key": "2",
      "type": "keydown",
      "timestamp": 12209.100000023842
    },
    {
      "key": "o",
      "type": "keyup",
      "timestamp": 12239.899999976158
    },
    {
      "key": "2",
      "type": "keyup",
      "timestamp": 12283.299999952316
    },
    {
      "key": "2",
      "type": "keydown",
      "timestamp": 12321.799999952316
    },
    {
      "key": "2",
      "type": "keyup",
      "timestamp": 12468.799999952316
    },
    {
      "key": "1",
      "type": "keydown",
      "timestamp": 12539.199999928474
    },
    {
      "key": "1",
      "type": "keyup",
      "timestamp": 12645.399999976158
    },
    {
      "key": "2",
      "type": "keydown",
      "timestamp": 12709
    },
    {
      "key": "Shift",
      "type": "keydown",
      "timestamp": 12800.299999952316
    },
    {
      "key": "@",
      "type": "keyup",
      "timestamp": 12814.5
    },
    {
      "key": "@",
      "type": "keydown",
      "timestamp": 12845.199999928474
    },
    {
      "key": "@",
      "type": "keyup",
      "timestamp": 12969
    },
    {
      "key": "#",
      "type": "keydown",
      "timestamp": 13085.899999976158
    },
    {
      "key": "Shift",
      "type": "keyup",
      "timestamp": 13125
    },
    {
      "key": "3",
      "type": "keyup",
      "timestamp": 13249.600000023842
    }
  ]
}